{
  "source_file": "今日登录客户明细_2026-07-23-16-40.xlsx",
  "email_subject": "【今日登录客户明细】2026-07-23-16-40",
  "data_date": "2026-07-23",
  "data_time": "16:40",
  "received_at": "2026-07-23T16:41:15+08:00",
  "updated_at": "2026-07-23T16:41:15+08:00",
  "source_rows": 59517,
  "unique_customers": 59504,
  "duplicate_rows": 13,
  "visit_field_definition": "door_or_phone",
  "order_without_cart_rows": 97,
  "summary": {
    "source_rows": 59517,
    "unique_customers": 59504,
    "duplicate_rows": 13,
    "login_customers": 59504,
    "visit_customers": 3052,
    "cart_customers": 19211,
    "order_customers": 16502,
    "order_without_cart_customers": 97
  },
  "rows": [
    {
      "region": "中部大区",
      "province": "公海",
      "industry": "单体",
      "login": 328,
      "visit": 0,
      "cart": 22,
      "order": 11,
      "visit_order": 0,
      "nonvisit_order": 11,
      "nonvisit_base": 328
    },
    {
      "region": "中部大区",
      "province": "公海",
      "industry": "连锁",
      "login": 14,
      "visit": 0,
      "cart": 3,
      "order": 2,
      "visit_order": 0,
      "nonvisit_order": 2,
      "nonvisit_base": 14
    },
    {
      "region": "中部大区",
      "province": "内蒙古",
      "industry": "单体",
      "login": 1961,
      "visit": 149,
      "cart": 734,
      "order": 676,
      "visit_order": 66,
      "nonvisit_order": 610,
      "nonvisit_base": 1812
    },
    {
      "region": "中部大区",
      "province": "内蒙古",
      "industry": "连锁",
      "login": 1,
      "visit": 0,
      "cart": 0,
      "order": 0,
      "visit_order": 0,
      "nonvisit_order": 0,
      "nonvisit_base": 1
    },
    {
      "region": "中部大区",
      "province": "天津",
      "industry": "单体",
      "login": 587,
      "visit": 46,
      "cart": 202,
      "order": 189,
      "visit_order": 19,
      "nonvisit_order": 170,
      "nonvisit_base": 541
    },
    {
      "region": "中部大区",
      "province": "天津",
      "industry": "连锁",
      "login": 3,
      "visit": 0,
      "cart": 0,
      "order": 1,
      "visit_order": 0,
      "nonvisit_order": 1,
      "nonvisit_base": 3
    },
    {
      "region": "中部大区",
      "province": "山西",
      "industry": "单体",
      "login": 1127,
      "visit": 53,
      "cart": 340,
      "order": 305,
      "visit_order": 17,
      "nonvisit_order": 288,
      "nonvisit_base": 1074
    },
    {
      "region": "中部大区",
      "province": "山西",
      "industry": "连锁",
      "login": 1,
      "visit": 0,
      "cart": 0,
      "order": 0,
      "visit_order": 0,
      "nonvisit_order": 0,
      "nonvisit_base": 1
    },
    {
      "region": "中部大区",
      "province": "河北",
      "industry": "单体",
      "login": 1606,
      "visit": 126,
      "cart": 411,
      "order": 368,
      "visit_order": 33,
      "nonvisit_order": 335,
      "nonvisit_base": 1480
    },
    {
      "region": "中部大区",
      "province": "河北",
      "industry": "连锁",
      "login": 2,
      "visit": 0,
      "cart": 2,
      "order": 1,
      "visit_order": 0,
      "nonvisit_order": 1,
      "nonvisit_base": 2
    },
    {
      "region": "中部大区",
      "province": "豫东",
      "industry": "单体",
      "login": 2465,
      "visit": 173,
      "cart": 826,
      "order": 709,
      "visit_order": 68,
      "nonvisit_order": 641,
      "nonvisit_base": 2292
    },
    {
      "region": "中部大区",
      "province": "豫西",
      "industry": "单体",
      "login": 2279,
      "visit": 187,
      "cart": 768,
      "order": 652,
      "visit_order": 52,
      "nonvisit_order": 600,
      "nonvisit_base": 2092
    },
    {
      "region": "中部大区",
      "province": "豫西",
      "industry": "连锁",
      "login": 3,
      "visit": 0,
      "cart": 1,
      "order": 1,
      "visit_order": 0,
      "nonvisit_order": 1,
      "nonvisit_base": 3
    },
    {
      "region": "其他区",
      "province": "上海",
      "industry": "连锁",
      "login": 1,
      "visit": 0,
      "cart": 0,
      "order": 0,
      "visit_order": 0,
      "nonvisit_order": 0,
      "nonvisit_base": 1
    },
    {
      "region": "其他区",
      "province": "公海",
      "industry": "单体",
      "login": 103,
      "visit": 0,
      "cart": 6,
      "order": 2,
      "visit_order": 0,
      "nonvisit_order": 2,
      "nonvisit_base": 103
    },
    {
      "region": "其他区",
      "province": "公海",
      "industry": "连锁",
      "login": 3,
      "visit": 0,
      "cart": 0,
      "order": 0,
      "visit_order": 0,
      "nonvisit_order": 0,
      "nonvisit_base": 3
    },
    {
      "region": "其他区",
      "province": "天津",
      "industry": "单体",
      "login": 8,
      "visit": 0,
      "cart": 4,
      "order": 4,
      "visit_order": 0,
      "nonvisit_order": 4,
      "nonvisit_base": 8
    },
    {
      "region": "其他区",
      "province": "河北",
      "industry": "单体",
      "login": 15,
      "visit": 0,
      "cart": 6,
      "order": 6,
      "visit_order": 0,
      "nonvisit_order": 6,
      "nonvisit_base": 15
    },
    {
      "region": "其他区",
      "province": "河北",
      "industry": "连锁",
      "login": 1,
      "visit": 0,
      "cart": 1,
      "order": 1,
      "visit_order": 0,
      "nonvisit_order": 1,
      "nonvisit_base": 1
    },
    {
      "region": "其他区",
      "province": "海南",
      "industry": "连锁",
      "login": 1,
      "visit": 0,
      "cart": 0,
      "order": 0,
      "visit_order": 0,
      "nonvisit_order": 0,
      "nonvisit_base": 1
    },
    {
      "region": "其他区",
      "province": "自营",
      "industry": "连锁",
      "login": 1,
      "visit": 0,
      "cart": 0,
      "order": 1,
      "visit_order": 0,
      "nonvisit_order": 1,
      "nonvisit_base": 1
    },
    {
      "region": "其他区",
      "province": "贵州",
      "industry": "单体",
      "login": 2,
      "visit": 0,
      "cart": 1,
      "order": 1,
      "visit_order": 0,
      "nonvisit_order": 1,
      "nonvisit_base": 2
    },
    {
      "region": "其他区",
      "province": "陕西",
      "industry": "连锁",
      "login": 1,
      "visit": 0,
      "cart": 0,
      "order": 0,
      "visit_order": 0,
      "nonvisit_order": 0,
      "nonvisit_base": 1
    },
    {
      "region": "北部大区",
      "province": "公海",
      "industry": "单体",
      "login": 511,
      "visit": 0,
      "cart": 45,
      "order": 20,
      "visit_order": 0,
      "nonvisit_order": 20,
      "nonvisit_base": 511
    },
    {
      "region": "北部大区",
      "province": "公海",
      "industry": "连锁",
      "login": 5,
      "visit": 0,
      "cart": 1,
      "order": 0,
      "visit_order": 0,
      "nonvisit_order": 0,
      "nonvisit_base": 5
    },
    {
      "region": "北部大区",
      "province": "吉林",
      "industry": "单体",
      "login": 1758,
      "visit": 105,
      "cart": 567,
      "order": 530,
      "visit_order": 48,
      "nonvisit_order": 482,
      "nonvisit_base": 1653
    },
    {
      "region": "北部大区",
      "province": "吉林",
      "industry": "连锁",
      "login": 3,
      "visit": 0,
      "cart": 0,
      "order": 0,
      "visit_order": 0,
      "nonvisit_order": 0,
      "nonvisit_base": 3
    },
    {
      "region": "北部大区",
      "province": "安徽",
      "industry": "单体",
      "login": 1803,
      "visit": 129,
      "cart": 606,
      "order": 551,
      "visit_order": 38,
      "nonvisit_order": 513,
      "nonvisit_base": 1674
    },
    {
      "region": "北部大区",
      "province": "安徽",
      "industry": "连锁",
      "login": 1,
      "visit": 0,
      "cart": 0,
      "order": 0,
      "visit_order": 0,
      "nonvisit_order": 0,
      "nonvisit_base": 1
    },
    {
      "region": "北部大区",
      "province": "山东",
      "industry": "单体",
      "login": 2251,
      "visit": 174,
      "cart": 710,
      "order": 622,
      "visit_order": 77,
      "nonvisit_order": 545,
      "nonvisit_base": 2077
    },
    {
      "region": "北部大区",
      "province": "山东",
      "industry": "连锁",
      "login": 2,
      "visit": 0,
      "cart": 0,
      "order": 0,
      "visit_order": 0,
      "nonvisit_order": 0,
      "nonvisit_base": 2
    },
    {
      "region": "北部大区",
      "province": "江苏",
      "industry": "单体",
      "login": 2203,
      "visit": 141,
      "cart": 719,
      "order": 666,
      "visit_order": 43,
      "nonvisit_order": 623,
      "nonvisit_base": 2062
    },
    {
      "region": "北部大区",
      "province": "江苏",
      "industry": "连锁",
      "login": 2,
      "visit": 0,
      "cart": 0,
      "order": 0,
      "visit_order": 0,
      "nonvisit_order": 0,
      "nonvisit_base": 2
    },
    {
      "region": "北部大区",
      "province": "浙北",
      "industry": "单体",
      "login": 1043,
      "visit": 102,
      "cart": 457,
      "order": 384,
      "visit_order": 38,
      "nonvisit_order": 346,
      "nonvisit_base": 941
    },
    {
      "region": "北部大区",
      "province": "浙北",
      "industry": "连锁",
      "login": 1,
      "visit": 0,
      "cart": 0,
      "order": 0,
      "visit_order": 0,
      "nonvisit_order": 0,
      "nonvisit_base": 1
    },
    {
      "region": "北部大区",
      "province": "浙南",
      "industry": "单体",
      "login": 1020,
      "visit": 75,
      "cart": 407,
      "order": 363,
      "visit_order": 29,
      "nonvisit_order": 334,
      "nonvisit_base": 945
    },
    {
      "region": "北部大区",
      "province": "福建",
      "industry": "单体",
      "login": 1177,
      "visit": 74,
      "cart": 410,
      "order": 366,
      "visit_order": 24,
      "nonvisit_order": 342,
      "nonvisit_base": 1103
    },
    {
      "region": "北部大区",
      "province": "福建",
      "industry": "连锁",
      "login": 1,
      "visit": 0,
      "cart": 0,
      "order": 0,
      "visit_order": 0,
      "nonvisit_order": 0,
      "nonvisit_base": 1
    },
    {
      "region": "北部大区",
      "province": "辽宁",
      "industry": "单体",
      "login": 1397,
      "visit": 99,
      "cart": 502,
      "order": 462,
      "visit_order": 40,
      "nonvisit_order": 422,
      "nonvisit_base": 1298
    },
    {
      "region": "北部大区",
      "province": "辽宁",
      "industry": "连锁",
      "login": 1,
      "visit": 0,
      "cart": 0,
      "order": 0,
      "visit_order": 0,
      "nonvisit_order": 0,
      "nonvisit_base": 1
    },
    {
      "region": "北部大区",
      "province": "黑龙江",
      "industry": "单体",
      "login": 1725,
      "visit": 111,
      "cart": 646,
      "order": 605,
      "visit_order": 44,
      "nonvisit_order": 561,
      "nonvisit_base": 1614
    },
    {
      "region": "华南大区",
      "province": "云南",
      "industry": "单体",
      "login": 1496,
      "visit": 135,
      "cart": 505,
      "order": 409,
      "visit_order": 49,
      "nonvisit_order": 360,
      "nonvisit_base": 1361
    },
    {
      "region": "华南大区",
      "province": "云南",
      "industry": "连锁",
      "login": 2,
      "visit": 0,
      "cart": 2,
      "order": 2,
      "visit_order": 0,
      "nonvisit_order": 2,
      "nonvisit_base": 2
    },
    {
      "region": "华南大区",
      "province": "公海",
      "industry": "单体",
      "login": 490,
      "visit": 0,
      "cart": 38,
      "order": 18,
      "visit_order": 0,
      "nonvisit_order": 18,
      "nonvisit_base": 490
    },
    {
      "region": "华南大区",
      "province": "公海",
      "industry": "连锁",
      "login": 11,
      "visit": 0,
      "cart": 1,
      "order": 1,
      "visit_order": 0,
      "nonvisit_order": 1,
      "nonvisit_base": 11
    },
    {
      "region": "华南大区",
      "province": "四川",
      "industry": "单体",
      "login": 1071,
      "visit": 71,
      "cart": 343,
      "order": 298,
      "visit_order": 17,
      "nonvisit_order": 281,
      "nonvisit_base": 1000
    },
    {
      "region": "华南大区",
      "province": "四川",
      "industry": "连锁",
      "login": 1,
      "visit": 0,
      "cart": 0,
      "order": 0,
      "visit_order": 0,
      "nonvisit_order": 0,
      "nonvisit_base": 1
    },
    {
      "region": "华南大区",
      "province": "广西",
      "industry": "单体",
      "login": 674,
      "visit": 46,
      "cart": 189,
      "order": 160,
      "visit_order": 17,
      "nonvisit_order": 143,
      "nonvisit_base": 628
    },
    {
      "region": "华南大区",
      "province": "江西",
      "industry": "单体",
      "login": 923,
      "visit": 46,
      "cart": 291,
      "order": 252,
      "visit_order": 16,
      "nonvisit_order": 236,
      "nonvisit_base": 877
    },
    {
      "region": "华南大区",
      "province": "江西",
      "industry": "连锁",
      "login": 1,
      "visit": 0,
      "cart": 0,
      "order": 0,
      "visit_order": 0,
      "nonvisit_order": 0,
      "nonvisit_base": 1
    },
    {
      "region": "华南大区",
      "province": "湖南",
      "industry": "单体",
      "login": 4744,
      "visit": 245,
      "cart": 2001,
      "order": 1580,
      "visit_order": 75,
      "nonvisit_order": 1505,
      "nonvisit_base": 4499
    },
    {
      "region": "华南大区",
      "province": "湖南",
      "industry": "连锁",
      "login": 3,
      "visit": 0,
      "cart": 0,
      "order": 0,
      "visit_order": 0,
      "nonvisit_order": 0,
      "nonvisit_base": 3
    },
    {
      "region": "华南大区",
      "province": "粤东",
      "industry": "单体",
      "login": 1404,
      "visit": 105,
      "cart": 431,
      "order": 377,
      "visit_order": 37,
      "nonvisit_order": 340,
      "nonvisit_base": 1299
    },
    {
      "region": "华南大区",
      "province": "粤东",
      "industry": "连锁",
      "login": 1,
      "visit": 0,
      "cart": 0,
      "order": 0,
      "visit_order": 0,
      "nonvisit_order": 0,
      "nonvisit_base": 1
    },
    {
      "region": "华南大区",
      "province": "粤西",
      "industry": "单体",
      "login": 1767,
      "visit": 126,
      "cart": 570,
      "order": 488,
      "visit_order": 29,
      "nonvisit_order": 459,
      "nonvisit_base": 1641
    },
    {
      "region": "华南大区",
      "province": "粤西",
      "industry": "连锁",
      "login": 5,
      "visit": 0,
      "cart": 1,
      "order": 3,
      "visit_order": 0,
      "nonvisit_order": 3,
      "nonvisit_base": 5
    },
    {
      "region": "华南大区",
      "province": "鄂东",
      "industry": "单体",
      "login": 1907,
      "visit": 139,
      "cart": 710,
      "order": 616,
      "visit_order": 63,
      "nonvisit_order": 553,
      "nonvisit_base": 1768
    },
    {
      "region": "华南大区",
      "province": "鄂西",
      "industry": "单体",
      "login": 1918,
      "visit": 109,
      "cart": 688,
      "order": 621,
      "visit_order": 35,
      "nonvisit_order": 586,
      "nonvisit_base": 1809
    },
    {
      "region": "华南大区",
      "province": "鄂西",
      "industry": "连锁",
      "login": 2,
      "visit": 0,
      "cart": 0,
      "order": 1,
      "visit_order": 0,
      "nonvisit_order": 1,
      "nonvisit_base": 2
    },
    {
      "region": "华南大区",
      "province": "重庆",
      "industry": "单体",
      "login": 1019,
      "visit": 50,
      "cart": 318,
      "order": 264,
      "visit_order": 16,
      "nonvisit_order": 248,
      "nonvisit_base": 969
    },
    {
      "region": "华南大区",
      "province": "重庆",
      "industry": "连锁",
      "login": 1,
      "visit": 0,
      "cart": 0,
      "order": 0,
      "visit_order": 0,
      "nonvisit_order": 0,
      "nonvisit_base": 1
    },
    {
      "region": "电销中心",
      "province": "电销一部",
      "industry": "单体",
      "login": 2356,
      "visit": 0,
      "cart": 602,
      "order": 490,
      "visit_order": 0,
      "nonvisit_order": 490,
      "nonvisit_base": 2356
    },
    {
      "region": "电销中心",
      "province": "电销三部",
      "industry": "单体",
      "login": 3563,
      "visit": 0,
      "cart": 822,
      "order": 693,
      "visit_order": 0,
      "nonvisit_order": 693,
      "nonvisit_base": 3563
    },
    {
      "region": "电销中心",
      "province": "电销三部",
      "industry": "连锁",
      "login": 5,
      "visit": 0,
      "cart": 2,
      "order": 2,
      "visit_order": 0,
      "nonvisit_order": 2,
      "nonvisit_base": 5
    },
    {
      "region": "电销中心",
      "province": "电销二部",
      "industry": "单体",
      "login": 3755,
      "visit": 0,
      "cart": 885,
      "order": 745,
      "visit_order": 0,
      "nonvisit_order": 745,
      "nonvisit_base": 3755
    },
    {
      "region": "电销中心",
      "province": "电销二部",
      "industry": "连锁",
      "login": 2,
      "visit": 0,
      "cart": 1,
      "order": 1,
      "visit_order": 0,
      "nonvisit_order": 1,
      "nonvisit_base": 2
    },
    {
      "region": "电销中心",
      "province": "电销四部",
      "industry": "单体",
      "login": 4567,
      "visit": 0,
      "cart": 1107,
      "order": 924,
      "visit_order": 0,
      "nonvisit_order": 924,
      "nonvisit_base": 4567
    },
    {
      "region": "电销中心",
      "province": "电销四部",
      "industry": "连锁",
      "login": 1,
      "visit": 0,
      "cart": 0,
      "order": 0,
      "visit_order": 0,
      "nonvisit_order": 0,
      "nonvisit_base": 1
    },
    {
      "region": "连锁业务中心",
      "province": "上海",
      "industry": "连锁",
      "login": 2,
      "visit": 0,
      "cart": 1,
      "order": 1,
      "visit_order": 0,
      "nonvisit_order": 1,
      "nonvisit_base": 2
    },
    {
      "region": "连锁业务中心",
      "province": "云南",
      "industry": "连锁",
      "login": 60,
      "visit": 8,
      "cart": 30,
      "order": 21,
      "visit_order": 2,
      "nonvisit_order": 19,
      "nonvisit_base": 52
    },
    {
      "region": "连锁业务中心",
      "province": "冀北",
      "industry": "连锁",
      "login": 93,
      "visit": 7,
      "cart": 50,
      "order": 42,
      "visit_order": 5,
      "nonvisit_order": 37,
      "nonvisit_base": 86
    },
    {
      "region": "连锁业务中心",
      "province": "冀南",
      "industry": "连锁",
      "login": 101,
      "visit": 8,
      "cart": 48,
      "order": 37,
      "visit_order": 1,
      "nonvisit_order": 36,
      "nonvisit_base": 93
    },
    {
      "region": "连锁业务中心",
      "province": "内蒙古",
      "industry": "连锁",
      "login": 46,
      "visit": 2,
      "cart": 31,
      "order": 26,
      "visit_order": 1,
      "nonvisit_order": 25,
      "nonvisit_base": 44
    },
    {
      "region": "连锁业务中心",
      "province": "吉林",
      "industry": "连锁",
      "login": 89,
      "visit": 9,
      "cart": 50,
      "order": 43,
      "visit_order": 6,
      "nonvisit_order": 37,
      "nonvisit_base": 80
    },
    {
      "region": "连锁业务中心",
      "province": "四川",
      "industry": "连锁",
      "login": 108,
      "visit": 14,
      "cart": 52,
      "order": 41,
      "visit_order": 8,
      "nonvisit_order": 33,
      "nonvisit_base": 94
    },
    {
      "region": "连锁业务中心",
      "province": "安徽",
      "industry": "连锁",
      "login": 96,
      "visit": 9,
      "cart": 41,
      "order": 35,
      "visit_order": 3,
      "nonvisit_order": 32,
      "nonvisit_base": 87
    },
    {
      "region": "连锁业务中心",
      "province": "山西",
      "industry": "连锁",
      "login": 39,
      "visit": 4,
      "cart": 28,
      "order": 21,
      "visit_order": 3,
      "nonvisit_order": 18,
      "nonvisit_base": 35
    },
    {
      "region": "连锁业务中心",
      "province": "广西",
      "industry": "连锁",
      "login": 40,
      "visit": 2,
      "cart": 20,
      "order": 17,
      "visit_order": 1,
      "nonvisit_order": 16,
      "nonvisit_base": 38
    },
    {
      "region": "连锁业务中心",
      "province": "新疆",
      "industry": "连锁",
      "login": 11,
      "visit": 3,
      "cart": 5,
      "order": 5,
      "visit_order": 2,
      "nonvisit_order": 3,
      "nonvisit_base": 8
    },
    {
      "region": "连锁业务中心",
      "province": "江苏",
      "industry": "连锁",
      "login": 103,
      "visit": 10,
      "cart": 53,
      "order": 45,
      "visit_order": 7,
      "nonvisit_order": 38,
      "nonvisit_base": 93
    },
    {
      "region": "连锁业务中心",
      "province": "江西",
      "industry": "连锁",
      "login": 50,
      "visit": 5,
      "cart": 31,
      "order": 27,
      "visit_order": 3,
      "nonvisit_order": 24,
      "nonvisit_base": 45
    },
    {
      "region": "连锁业务中心",
      "province": "浙江",
      "industry": "连锁",
      "login": 96,
      "visit": 5,
      "cart": 53,
      "order": 44,
      "visit_order": 3,
      "nonvisit_order": 41,
      "nonvisit_base": 91
    },
    {
      "region": "连锁业务中心",
      "province": "海南",
      "industry": "单体",
      "login": 17,
      "visit": 1,
      "cart": 6,
      "order": 5,
      "visit_order": 1,
      "nonvisit_order": 4,
      "nonvisit_base": 16
    },
    {
      "region": "连锁业务中心",
      "province": "海南",
      "industry": "连锁",
      "login": 15,
      "visit": 2,
      "cart": 8,
      "order": 6,
      "visit_order": 1,
      "nonvisit_order": 5,
      "nonvisit_base": 13
    },
    {
      "region": "连锁业务中心",
      "province": "湖北",
      "industry": "连锁",
      "login": 162,
      "visit": 14,
      "cart": 92,
      "order": 77,
      "visit_order": 6,
      "nonvisit_order": 71,
      "nonvisit_base": 148
    },
    {
      "region": "连锁业务中心",
      "province": "湖南",
      "industry": "连锁",
      "login": 135,
      "visit": 14,
      "cart": 88,
      "order": 73,
      "visit_order": 9,
      "nonvisit_order": 64,
      "nonvisit_base": 121
    },
    {
      "region": "连锁业务中心",
      "province": "甘青宁",
      "industry": "连锁",
      "login": 24,
      "visit": 2,
      "cart": 9,
      "order": 7,
      "visit_order": 1,
      "nonvisit_order": 6,
      "nonvisit_base": 22
    },
    {
      "region": "连锁业务中心",
      "province": "福建",
      "industry": "单体",
      "login": 1,
      "visit": 0,
      "cart": 0,
      "order": 0,
      "visit_order": 0,
      "nonvisit_order": 0,
      "nonvisit_base": 1
    },
    {
      "region": "连锁业务中心",
      "province": "福建",
      "industry": "连锁",
      "login": 57,
      "visit": 8,
      "cart": 35,
      "order": 25,
      "visit_order": 5,
      "nonvisit_order": 20,
      "nonvisit_base": 49
    },
    {
      "region": "连锁业务中心",
      "province": "粤东",
      "industry": "单体",
      "login": 2,
      "visit": 0,
      "cart": 2,
      "order": 1,
      "visit_order": 0,
      "nonvisit_order": 1,
      "nonvisit_base": 2
    },
    {
      "region": "连锁业务中心",
      "province": "粤东",
      "industry": "连锁",
      "login": 123,
      "visit": 16,
      "cart": 78,
      "order": 65,
      "visit_order": 9,
      "nonvisit_order": 56,
      "nonvisit_base": 107
    },
    {
      "region": "连锁业务中心",
      "province": "粤西",
      "industry": "单体",
      "login": 3,
      "visit": 0,
      "cart": 1,
      "order": 0,
      "visit_order": 0,
      "nonvisit_order": 0,
      "nonvisit_base": 3
    },
    {
      "region": "连锁业务中心",
      "province": "粤西",
      "industry": "连锁",
      "login": 98,
      "visit": 13,
      "cart": 62,
      "order": 47,
      "visit_order": 4,
      "nonvisit_order": 43,
      "nonvisit_base": 85
    },
    {
      "region": "连锁业务中心",
      "province": "西藏",
      "industry": "单体",
      "login": 1,
      "visit": 0,
      "cart": 1,
      "order": 1,
      "visit_order": 0,
      "nonvisit_order": 1,
      "nonvisit_base": 1
    },
    {
      "region": "连锁业务中心",
      "province": "西藏",
      "industry": "连锁",
      "login": 1,
      "visit": 0,
      "cart": 1,
      "order": 0,
      "visit_order": 0,
      "nonvisit_order": 0,
      "nonvisit_base": 1
    },
    {
      "region": "连锁业务中心",
      "province": "豫东",
      "industry": "连锁",
      "login": 103,
      "visit": 13,
      "cart": 55,
      "order": 47,
      "visit_order": 5,
      "nonvisit_order": 42,
      "nonvisit_base": 90
    },
    {
      "region": "连锁业务中心",
      "province": "豫西",
      "industry": "连锁",
      "login": 130,
      "visit": 14,
      "cart": 69,
      "order": 58,
      "visit_order": 10,
      "nonvisit_order": 48,
      "nonvisit_base": 116
    },
    {
      "region": "连锁业务中心",
      "province": "贵州",
      "industry": "连锁",
      "login": 26,
      "visit": 2,
      "cart": 13,
      "order": 10,
      "visit_order": 1,
      "nonvisit_order": 9,
      "nonvisit_base": 24
    },
    {
      "region": "连锁业务中心",
      "province": "辽宁",
      "industry": "连锁",
      "login": 98,
      "visit": 9,
      "cart": 51,
      "order": 38,
      "visit_order": 5,
      "nonvisit_order": 33,
      "nonvisit_base": 89
    },
    {
      "region": "连锁业务中心",
      "province": "重庆",
      "industry": "连锁",
      "login": 82,
      "visit": 8,
      "cart": 41,
      "order": 33,
      "visit_order": 4,
      "nonvisit_order": 29,
      "nonvisit_base": 74
    },
    {
      "region": "连锁业务中心",
      "province": "陕西",
      "industry": "单体",
      "login": 1,
      "visit": 0,
      "cart": 0,
      "order": 0,
      "visit_order": 0,
      "nonvisit_order": 0,
      "nonvisit_base": 1
    },
    {
      "region": "连锁业务中心",
      "province": "陕西",
      "industry": "连锁",
      "login": 47,
      "visit": 4,
      "cart": 27,
      "order": 18,
      "visit_order": 2,
      "nonvisit_order": 16,
      "nonvisit_base": 43
    },
    {
      "region": "连锁业务中心",
      "province": "鲁东",
      "industry": "连锁",
      "login": 107,
      "visit": 7,
      "cart": 54,
      "order": 44,
      "visit_order": 2,
      "nonvisit_order": 42,
      "nonvisit_base": 100
    },
    {
      "region": "连锁业务中心",
      "province": "鲁西",
      "industry": "连锁",
      "login": 109,
      "visit": 10,
      "cart": 48,
      "order": 36,
      "visit_order": 3,
      "nonvisit_order": 33,
      "nonvisit_base": 99
    },
    {
      "region": "连锁业务中心",
      "province": "黑龙江",
      "industry": "连锁",
      "login": 122,
      "visit": 13,
      "cart": 73,
      "order": 62,
      "visit_order": 6,
      "nonvisit_order": 56,
      "nonvisit_base": 109
    }
  ]
}